sphinx_autodoc_bmotif/__init__.py
sphinx_autodoc_bmotif/py.typed
sphinx_autodoc_bmotif-0.1.6.dist-info/METADATA
sphinx_autodoc_bmotif-0.1.6.dist-info/WHEEL
sphinx_autodoc_bmotif-0.1.6.dist-info/licenses/LICENSE
sphinx_autodoc_bmotif-0.1.6.dist-info/RECORD
